{
  "agendamentos":
[
      {
        "id": "9239292",
        "moradorNome": "Suzanna",
        "enderecoColeta": "Rua Doze",
        "cooperativa": "Cooperativa Recicla",
        "diaColeta": "11/02/2021",
        "statusPedido": "aprovado",
        "statusColeta": "agendada"
      },
      {
        "id": "9000000",
        "moradorNome": "ANAAAA",
        "enderecoColeta": "Rua Doze",
        "cooperativa": "Cooperativa Recicla",
        "diaColeta": "11/02/2021",
        "statusPedido": "aprovado",
        "statusColeta": "feita"
      }
 ]

 }
